ckenchanter/__init__.py
ckenchanter-1.2.0.dist-info/LICENSE.txt
ckenchanter-1.2.0.dist-info/METADATA
ckenchanter-1.2.0.dist-info/RECORD
ckenchanter-1.2.0.dist-info/WHEEL
ckenchanter-1.2.0.dist-info/top_level.txt
